kotl_ignis/__init__.py
kotl_ignis/__main__.py
kotl_ignis/settings.py
kotl_ignis/utils.py
kotl_ignis/colorschemes/3024.dark.json
kotl_ignis/colorschemes/3024.light.json
kotl_ignis/colorschemes/Baskerville-Count-Von-Count.json
kotl_ignis/colorschemes/Baskerville-Eldorado-dark.json
kotl_ignis/colorschemes/DOOMICIDE-darkocean.json
kotl_ignis/colorschemes/Gslob-nature-suede.json
kotl_ignis/colorschemes/Gutterslob-aikofog.json
kotl_ignis/colorschemes/Gutterslob-lightwhite.json
kotl_ignis/colorschemes/Muse.json
kotl_ignis/colorschemes/Muzieca-lowcontrast.json
kotl_ignis/colorschemes/Muzieca-mono.json
kotl_ignis/colorschemes/Muzieca-pastel-white.json
kotl_ignis/colorschemes/NumixDarkest.json
kotl_ignis/colorschemes/OK100-Matrix.json
kotl_ignis/colorschemes/Rooster-SOS.json
kotl_ignis/colorschemes/Tartan.json
kotl_ignis/colorschemes/Visiblue.json
kotl_ignis/colorschemes/ashes.dark.json
kotl_ignis/colorschemes/ashes.light.json
kotl_ignis/colorschemes/astromouse.json
kotl_ignis/colorschemes/atelierdune.dark.json
kotl_ignis/colorschemes/atelierdune.light.json
kotl_ignis/colorschemes/atelierforest.dark.json
kotl_ignis/colorschemes/atelierforest.light.json
kotl_ignis/colorschemes/atelierheath.dark.json
kotl_ignis/colorschemes/atelierheath.light.json
kotl_ignis/colorschemes/atelierlakeside.dark.json
kotl_ignis/colorschemes/atelierlakeside.light.json
kotl_ignis/colorschemes/atelierseaside.dark.json
kotl_ignis/colorschemes/atelierseaside.light.json
kotl_ignis/colorschemes/baskerville-FarSide.json
kotl_ignis/colorschemes/baskerville-ivory-dark.json
kotl_ignis/colorschemes/baskerville-ivorylight.json
kotl_ignis/colorschemes/baskerville-lost-woods.json
kotl_ignis/colorschemes/belge.json
kotl_ignis/colorschemes/bespin.dark.json
kotl_ignis/colorschemes/bespin.light.json
kotl_ignis/colorschemes/bitmute.json
kotl_ignis/colorschemes/bleh-1.json
kotl_ignis/colorschemes/brewer.dark.json
kotl_ignis/colorschemes/brewer.light.json
kotl_ignis/colorschemes/chalk.dark.json
kotl_ignis-0.1.1.dist-info/LICENSE
kotl_ignis-0.1.1.dist-info/METADATA
kotl_ignis-0.1.1.dist-info/WHEEL
kotl_ignis-0.1.1.dist-info/entry_points.txt
kotl_ignis-0.1.1.dist-info/top_level.txt
kotl_ignis-0.1.1.dist-info/RECORD
