Metadata-Version: 2.1
Name: kotl-ignis
Version: 0.1.1
Summary: Change color-schemes
Author: Graphity
License: MIT License        
Project-URL: Homepage, https://github.com/Graphity/kotl
Project-URL: Bug Tracker, https://github.com/Graphity/kotl/issues
Classifier: Programming Language :: Python :: 3
Classifier: License :: OSI Approved :: MIT License
Classifier: Operating System :: Unix
Requires-Python: >=3.7
License-File: LICENSE
Requires-Dist: click
